[
    {
        "position": {
            "lat": 43.47390507332727,
            "lng": -112.03938762208882
        },
        "title": "Tautphaus Park",
        "type": "park",
        "description": "hahahahhaha",
        "image": "images/1.jpg",
        "link": "https://www.google.com/search?q=test&rlz=1C1MMCH_enUS1121US1121&oq=test&gs_lcrp=EgZjaHJvbWUyDwgAEEUYORiDARixAxiABDIKCAEQABixAxiABDIHCAIQABiABDIKCAMQABixAxiABDINCAQQLhivARjHARiABDIGCAUQRRg8MgYIBhBFGDwyBggHEEUYPNIBBzU0M2owajeoAgiwAgHxBdKJNDEhmKSI8QXSiTQxIZikiA&sourceid=chrome&ie=UTF-8"
    },
    {
        "position": {
            "lat": 43.496617379729955,
            "lng": -112.04395167424477
        },
        "title": "Idaho Falls Greenbelt",
        "type": "park"
    },
    {
        "position": {
            "lat": 43.51485308134474,
            "lng": -112.05154234540836
        },
        "title": "Russell A. Freeman Park",
        "type": "park"
    },
    {
        "position": {
            "lat": 43.492605105497105,
            "lng": -112.04494828958718
        },
        "title": "Japanese Friendship Garden",
        "type": "park"
    },
    {
        "position": {
            "lat": 43.486678424364605,
            "lng": -112.04765252331809
        },
        "title": "Rock Gardens",
        "type": "park"
    },
    {
        "position": {
            "lat": 43.47738720374111,
            "lng": -112.04447031655747
        },
        "title": " Rollandet Park",
        "type": "park"
    },
    {
        "position": {
            "lat": 43.47222520529306,
            "lng": -112.0413356200504
        },
        "title": "Idaho Falls Zoo",
        "type": "park"
    },
    {
        "position": {
            "lat": 43.506188745845925,
            "lng": -112.07067430463329
        },
        "title": "Reinhart Park",
        "type": "park"
    },
    {
        "position": {
            "lat": 43.50125569319502,
            "lng": -112.02283985302934
        },
        "title": "Central Park",
        "type": "park"
    },
    {
        "position": {
            "lat": 43.490560109345765,
            "lng": -112.03812758773846
        },
        "title": "Museum of Idaho",
        "type": "museum"
    },
    {
        "position": {
            "lat": 43.49035029197007,
            "lng": -112.04542110698067
        },
        "title": "The Art Museum of Eastern Idaho",
        "type": "museum"
    },
    {
        "position": {
            "lat": 43.491107204399405,
            "lng": -112.04021905115837
        },
        "title": "ARTitorium on Broadway",
        "type": "museum"
    },
    {
        "position": {
            "lat": 43.49356276562977,
            "lng": -112.01377246650046
        },
        "title": "Collectors Corner Museum",
        "type": "museum"
    },
    {
        "position": {
            "lat": 43.49347241948041,
            "lng": -112.0413784647251
        },
        "title": "Willard Arts Center (Colonial Theatre)",
        "type": "museum"
    },
    {
        "position": {
            "lat": 43.491219330857,
            "lng": -112.0498700344276
        },
        "title": "Eagle Rock Fountain",
        "type": "historical"
    },
    {
        "position": {
            "lat": 43.50578838678016,
            "lng": -112.04575016158306
        }
    },
    {
        "position": {
            "lat": 43.50031686603399,
            "lng": -112.04078398958671
        },
        "title": "Idaho Falls Temple Visitors' Center",
        "type": "historical"
    },
    {
        "position": {
            "lat": 43.492221723137675,
            "lng": -112.03989894540942
        },
        "title": "Idaho Falls Downtown Development Corporation",
        "type": "historical"
    },
    {
        "position": {
            "lat": 43.494333988927096,
            "lng": -112.03837911525265
        },
        "title": "City Building",
        "type": "historical"
    },
    {
        "position": {
            "lat": 43.49238135719048,
            "lng": -112.04074765950314
        },
        "title": "Hasbrouck Building",
        "type": "historical"
    },
    {
        "position": {
            "lat": 43.49339176966972,
            "lng": -112.03843577609369
        },
        "title": "Montgomery Ward Building",
        "type": "historical"
    }
]